moudle/__init__.py
moudle/core.py
jingziqi-0.0.1.dist-info/LICENSE
jingziqi-0.0.1.dist-info/METADATA
jingziqi-0.0.1.dist-info/WHEEL
jingziqi-0.0.1.dist-info/top_level.txt
jingziqi-0.0.1.dist-info/RECORD
